CHANGELOG.rst
MANIFEST.in
README.rst
setup.py
ease_restapi/__init__.py
ease_restapi/config.py
ease_restapi.egg-info/PKG-INFO
ease_restapi.egg-info/SOURCES.txt
ease_restapi.egg-info/dependency_links.txt
ease_restapi.egg-info/requires.txt
ease_restapi.egg-info/top_level.txt
ease_restapi.egg-info/zip-safe
ease_restapi/demo/__init__.py
ease_restapi/demo/admin.py
ease_restapi/demo/common.py
ease_restapi/demo/models.py
ease_restapi/demo/locale/zh_CN/LC_MESSAGES/django.mo
ease_restapi/demo/locale/zh_CN/LC_MESSAGES/django.po
ease_restapi/service/__init__.py
ease_restapi/service/auth.py
ease_restapi/service/base.py
ease_restapi/service/ease_auth.py
ease_restapi/service/ease_batch.py
ease_restapi/service/ease_black.py
ease_restapi/service/ease_file.py
ease_restapi/service/ease_friend.py
ease_restapi/service/ease_group.py
ease_restapi/service/ease_message.py
ease_restapi/service/ease_msgdata.py
ease_restapi/service/ease_records.py
ease_restapi/service/ease_select.py
ease_restapi/service/ease_user.py
ease_restapi/simplify/__init__.py
ease_restapi/simplify/bridge.py
ease_restapi/simplify/usage.py
project_demo/manage.py
project_demo/demo/__init__.py
project_demo/demo/common.py
project_demo/demo/config.py
project_demo/demo/demo.py
project_demo/demo/urls.py
project_demo/demo/views.py
project_demo/project/__init__.py
project_demo/project/settings.py
project_demo/project/urls.py
project_demo/project/wsgi.py